tune_sklearn/__init__.py
tune_sklearn/_detect_booster.py
tune_sklearn/_trainable.py
tune_sklearn/_version.py
tune_sklearn/list_searcher.py
tune_sklearn/tune_basesearch.py
tune_sklearn/tune_gridsearch.py
tune_sklearn/tune_search.py
tune_sklearn/utils.py
tune_sklearn-0.5.0.dist-info/LICENSE
tune_sklearn-0.5.0.dist-info/METADATA
tune_sklearn-0.5.0.dist-info/WHEEL
tune_sklearn-0.5.0.dist-info/top_level.txt
tune_sklearn-0.5.0.dist-info/RECORD
