Metadata-Version: 2.1
Name: tune-sklearn
Version: 0.5.0
Summary: A drop-in replacement for Scikit-Learn's GridSearchCV / RandomizedSearchCV with cutting edge hyperparameter tuning techniques.
Home-page: https://github.com/ray-project/tune-sklearn
Author: Michael Chau, Anthony Yu, and Ray Team
Author-email: ray-dev@googlegroups.com
License: Apache 2.0
License-File: LICENSE
Requires-Dist: scikit-learn
Requires-Dist: scipy
Requires-Dist: ray[tune] (>=2.7.1)
Requires-Dist: numpy (>=1.16)
